msopt/__init__.py
msopt/api.cpython-311-darwin.so
msopt/api.cpython-311-x86_64-linux-gnu.so
msopt/msopt.cpython-311-darwin.so
msopt/msopt.cpython-311-x86_64-linux-gnu.so
msopt-0.0.8.dist-info/METADATA
msopt-0.0.8.dist-info/WHEEL
msopt-0.0.8.dist-info/RECORD
